dash_draggable/DashDraggable.py
dash_draggable/DashDraggable2.py
dash_draggable/DashDraggableResponsive.py
dash_draggable/DashboardItem.py
dash_draggable/DashboardItemResponsive.py
dash_draggable/DragItem.py
dash_draggable/DraggableDashboard.py
dash_draggable/DraggableDashboardResponsive.py
dash_draggable/GridLayout.py
dash_draggable/ResponsiveGridLayout.py
dash_draggable/__init__.py
dash_draggable/_imports_.py
dash_draggable/dash_draggable.min.js
dash_draggable/dash_draggable.min.js.map
dash_draggable/demo.py
dash_draggable/metadata.json
dash_draggable/package-info.json
dash_draggable/test.py
dash_draggable-0.1.2.dist-info/LICENSE
dash_draggable-0.1.2.dist-info/METADATA
dash_draggable-0.1.2.dist-info/WHEEL
dash_draggable-0.1.2.dist-info/top_level.txt
dash_draggable-0.1.2.dist-info/RECORD
